share_df/__init__.py
share_df/models.py
share_df/server.py
share_df/static/css/styles.css
share_df/static/css/version-history.css
share_df/static/js/editor.js
share_df/static/templates/editor.html
share_df-1.5.2.dist-info/LICENSE
share_df-1.5.2.dist-info/METADATA
share_df-1.5.2.dist-info/WHEEL
share_df-1.5.2.dist-info/RECORD
