Metadata-Version: 2.1
Name: share-df
Version: 1.5.2
Summary: Share and Edit Pandas/Polars Dataframes with a Link!
Home-page: https://github.com/RohanAdwankar/share-df
Author: Rohan Adwankar
Author-email: rohan.adwankar@gmail.com
Requires-Python: >=3.9,<4.0
Classifier: Programming Language :: Python :: 3
Classifier: Programming Language :: Python :: 3.9
Classifier: Programming Language :: Python :: 3.10
Classifier: Programming Language :: Python :: 3.11
Classifier: Programming Language :: Python :: 3.12
Classifier: Programming Language :: Python :: 3.13
Requires-Dist: boto3 (>=1.34.51,<2.0.0)
Requires-Dist: cryptography (>=44.0.3,<45.0.0)
Requires-Dist: fastapi (>=0.115.5,<0.116.0)
Requires-Dist: ipykernel (>=6.29.3,<7.0.0)
Requires-Dist: jinja2 (>=3.1.5,<4.0.0)
Requires-Dist: nest_asyncio (>=1.6.0,<2.0.0)
Requires-Dist: ngrok (>=1.4.0,<2.0.0)
Requires-Dist: pandas (>=2.2.3,<3.0.0)
Requires-Dist: polars (>=1.21.0,<2.0.0)
Requires-Dist: pyarrow (>=19.0.0,<20.0.0)
Requires-Dist: python-dotenv (>=1.0.1,<2.0.0)
Requires-Dist: requests (>=2.31.0,<3.0.0)
Requires-Dist: uvicorn (>=0.32.1,<0.33.0)
Project-URL: Repository, https://github.com/RohanAdwankar/share-df
